freeq/__init__.py
freeq/freeq.py
freeq/__pycache__/__init__.cpython-312.pyc
freeq/__pycache__/freeq.cpython-312.pyc
freeq-0.0.21.dist-info/licenses/LICENSE
freeq-0.0.21.dist-info/METADATA
freeq-0.0.21.dist-info/WHEEL
freeq-0.0.21.dist-info/top_level.txt
freeq-0.0.21.dist-info/RECORD
