Metadata-Version: 2.4
Name: freeq
Version: 0.0.21
Summary: Zero-setup queue with e2e encryption for free in 1 line of code
Author-email: Viktor Hronec <zamr666@gmail.com>
License:                                  Apache License
Project-URL: Homepage, https://github.com/hronecviktor/freeq
Project-URL: Bug Tracker, https://github.com/hronecviktor/freeq/issues
Keywords: queue,easy,message queue,zero-setup
Classifier: Programming Language :: Python :: 3
Classifier: License :: OSI Approved :: Apache Software License
Classifier: Operating System :: OS Independent
Requires-Python: >=3.8
License-File: LICENSE
Requires-Dist: certifi==2025.8.3
Requires-Dist: cffi==2.0.0
Requires-Dist: charset-normalizer==3.4.3
Requires-Dist: cryptography==45.0.7
Requires-Dist: idna==3.10
Requires-Dist: pycparser==2.23
Requires-Dist: requests==2.32.5
Requires-Dist: urllib3==2.5.0
Requires-Dist: zstandard==0.25.0
Dynamic: license-file
